dbxsql/.env.example
dbxsql/__init__.py
dbxsql/auth.py
dbxsql/connection.py
dbxsql/exceptions.py
dbxsql/main.py
dbxsql/models.py
dbxsql/query_handler.py
dbxsql/settings.py
dbxsql-1.0.5.dist-info/METADATA
dbxsql-1.0.5.dist-info/WHEEL
dbxsql-1.0.5.dist-info/entry_points.txt
dbxsql-1.0.5.dist-info/licenses/LICENSE
dbxsql-1.0.5.dist-info/RECORD
