Metadata-Version: 2.4
Name: dbxsql
Version: 1.0.5
Summary: A comprehensive Databricks SQL handler with Pydantic models, OAuth authentication, and connection management
Project-URL: Homepage, https://github.com/kavodsky/dbxsql
Project-URL: Repository, https://github.com/kavodsky/dbxsql.git
Project-URL: Documentation, https://github.com/kavodsky/dbxsql#readme
Project-URL: Issues, https://github.com/kavodsky/dbxsql/issues
Author-email: Andras Gyacsok <atti.dyachok@gmail.com>
Maintainer-email: Andras Gyacsok <atti.dyachok@gmail.com>
License: MIT
License-File: LICENSE
Keywords: database,databricks,oauth,pydantic,sql
Classifier: Development Status :: 4 - Beta
Classifier: Intended Audience :: Developers
Classifier: License :: OSI Approved :: MIT License
Classifier: Operating System :: OS Independent
Classifier: Programming Language :: Python :: 3
Classifier: Programming Language :: Python :: 3.10
Classifier: Programming Language :: Python :: 3.11
Classifier: Programming Language :: Python :: 3.12
Classifier: Topic :: Database
Classifier: Topic :: Software Development :: Libraries :: Python Modules
Requires-Python: >=3.10
Requires-Dist: certifi>=2025.8.3
Requires-Dist: databricks-sdk>=0.62.0
Requires-Dist: databricks-sql-connector>=4.1.2
Requires-Dist: pyarrow>=21.0.0
Requires-Dist: pydantic-settings>=2.10.1
Requires-Dist: pydantic>=2.11.7
Provides-Extra: dev
Requires-Dist: black; extra == 'dev'
Requires-Dist: flake8; extra == 'dev'
Requires-Dist: mypy; extra == 'dev'
Requires-Dist: pre-commit; extra == 'dev'
Requires-Dist: pytest>=8.4.1; extra == 'dev'
